claircli/__init__.py
claircli/__version__.py
claircli/clair.py
claircli/cli.py
claircli/docker_image.py
claircli/docker_registry.py
claircli/http_handler.py
claircli/report.py
claircli/utils.py
claircli/templates/html-report.j2
claircli-1.3.dist-info/LICENSE
claircli-1.3.dist-info/METADATA
claircli-1.3.dist-info/WHEEL
claircli-1.3.dist-info/entry_points.txt
claircli-1.3.dist-info/top_level.txt
claircli-1.3.dist-info/RECORD
